apipack/__init__.py
apipack/cli.py
apipack/config/__init__.py
apipack/config/schemas.py
apipack/config/settings.py
apipack/core/__init__.py
apipack/core/deployer.py
apipack/core/engine.py
apipack/core/generator.py
apipack/core/parser.py
apipack/core/validator.py
apipack/llm/__init__.py
apipack/llm/mistral_client.py
apipack/llm/prompt_manager.py
apipack/llm/response_parser.py
apipack/plugins/__init__.py
apipack/plugins/base_plugin.py
apipack/templates/__init__.py
apipack/templates/registry.py
apipack/utils/__init__.py
apipack/utils/docker_utils.py
apipack/utils/file_utils.py
apipack/utils/test_utils.py
apipack-0.1.1.dist-info/licenses/LICENSE
apipack-0.1.1.dist-info/METADATA
apipack-0.1.1.dist-info/WHEEL
apipack-0.1.1.dist-info/entry_points.txt
apipack-0.1.1.dist-info/top_level.txt
apipack-0.1.1.dist-info/RECORD
