Metadata-Version: 2.4
Name: apipack
Version: 0.1.1
Summary: Automated API package generator with LLM integration
Home-page: https://github.com/apipack/apipack
Author: APIpack Team
Author-email: APIpack Team <team@apipack.dev>
Maintainer-email: APIpack Team <team@apipack.dev>
License: MIT
Project-URL: Homepage, https://github.com/apipack/apipack
Project-URL: Documentation, https://apipack.readthedocs.io/
Project-URL: Repository, https://github.com/apipack/apipack
Project-URL: Bug Tracker, https://github.com/apipack/apipack/issues
Project-URL: Changelog, https://github.com/apipack/apipack/blob/main/CHANGELOG.md
Keywords: api,generator,llm,mistral,templates,automation
Classifier: Development Status :: 3 - Alpha
Classifier: Intended Audience :: Developers
Classifier: License :: OSI Approved :: MIT License
Classifier: Programming Language :: Python :: 3
Classifier: Programming Language :: Python :: 3.8
Classifier: Programming Language :: Python :: 3.9
Classifier: Programming Language :: Python :: 3.10
Classifier: Programming Language :: Python :: 3.11
Classifier: Programming Language :: Python :: 3.12
Classifier: Topic :: Software Development :: Code Generators
Classifier: Topic :: Software Development :: Libraries :: Python Modules
Classifier: Topic :: Internet :: WWW/HTTP :: HTTP Servers
Requires-Python: >=3.8
License-File: LICENSE
Requires-Dist: click>=8.0.0
Requires-Dist: jinja2>=3.0.0
Requires-Dist: pyyaml>=6.0
Requires-Dist: pydantic>=2.0.0
Requires-Dist: requests>=2.28.0
Requires-Dist: aiohttp>=3.8.0
Requires-Dist: ollama>=0.1.7
Requires-Dist: docker>=6.0.0
Requires-Dist: rich>=13.0.0
Requires-Dist: typer>=0.9.0
Requires-Dist: watchdog>=3.0.0
Requires-Dist: gitpython>=3.1.0
Provides-Extra: dev
Requires-Dist: pytest>=7.0; extra == "dev"
Requires-Dist: pytest-cov>=4.0; extra == "dev"
Requires-Dist: pytest-asyncio>=0.21.0; extra == "dev"
Requires-Dist: black>=23.0; extra == "dev"
Requires-Dist: flake8>=6.0; extra == "dev"
Requires-Dist: mypy>=1.0; extra == "dev"
Requires-Dist: pre-commit>=3.0; extra == "dev"
Requires-Dist: isort>=5.12; extra == "dev"
Provides-Extra: docs
Requires-Dist: sphinx>=6.0; extra == "docs"
Requires-Dist: sphinx-rtd-theme>=1.2; extra == "docs"
Requires-Dist: myst-parser>=2.0; extra == "docs"
Requires-Dist: sphinx-autodoc-typehints>=1.23; extra == "docs"
Provides-Extra: test
Requires-Dist: pytest>=7.0; extra == "test"
Requires-Dist: pytest-cov>=4.0; extra == "test"
Requires-Dist: pytest-asyncio>=0.21.0; extra == "test"
Requires-Dist: httpx>=0.24.0; extra == "test"
Requires-Dist: responses>=0.23.0; extra == "test"
Provides-Extra: deploy
Requires-Dist: kubernetes>=26.0; extra == "deploy"
Requires-Dist: ansible>=8.0; extra == "deploy"
Requires-Dist: terraform>=1.0; extra == "deploy"
Provides-Extra: all
Requires-Dist: apipack[deploy,dev,docs,test]; extra == "all"
Dynamic: author
Dynamic: home-page
Dynamic: license-file
Dynamic: requires-python
